tfm_sdk/.DS_Store
tfm_sdk/__init__.py
tfm_sdk/api/__init__.py
tfm_sdk/api/base.py
tfm_sdk/api/chain.py
tfm_sdk/api/clients.py
tfm_sdk/api/dex.py
tfm_sdk/api/exceptions.py
tfm_sdk/api/ibc/__init__.py
tfm_sdk/api/ibc/chain.py
tfm_sdk/api/ibc/swap.py
tfm_sdk/api/ibc/transfer.py
tfm_sdk/api/price.py
tfm_sdk/clients.py
tfm_sdk/config.py
tfm_sdk/exceptions.py
tfm_sdk/handlers/__init__.py
tfm_sdk/handlers/chains.py
tfm_sdk/handlers/dex.py
tfm_sdk/handlers/mixins.py
tfm_sdk/handlers/swaps.py
tfm_sdk/handlers/tokens.py
tfm_sdk/handlers/transfer.py
tfm_sdk/types/__init__.py
tfm_sdk/types/dataclasses.py
tfm_sdk/types/enums.py
tfm_sdk/types/mixins.py
tfm_sdk/types/utils.py
tfm_sdk-0.2.1.dist-info/METADATA
tfm_sdk-0.2.1.dist-info/WHEEL
tfm_sdk-0.2.1.dist-info/RECORD
