Metadata-Version: 2.1
Name: tfm-sdk
Version: 0.2.1
Summary: The TFM SDK package allows easy access to the TFM API, providing functionality for interacting with pricing, dex aggregator and ibc transfer and swap.
Home-page: https://tfm.com
License: MIT
Keywords: tfm,sdk,bridge,swap,route,ibc
Author: TFM
Author-email: info@tfm.com
Requires-Python: >=3.10,<4.0
Classifier: License :: OSI Approved :: MIT License
Classifier: Programming Language :: Python :: 3
Classifier: Programming Language :: Python :: 3.10
Classifier: Programming Language :: Python :: 3.11
Requires-Dist: aiohttp (>=3.8.4,<4.0.0)
Requires-Dist: wrapt (>=1.15.0,<2.0.0)
Project-URL: Documentation, https://docs.tfm.com/dev-docs/sdk
